ask_cli/main.py
ask_connect_cli-0.1.3.dist-info/METADATA
ask_connect_cli-0.1.3.dist-info/WHEEL
ask_connect_cli-0.1.3.dist-info/entry_points.txt
ask_connect_cli-0.1.3.dist-info/top_level.txt
ask_connect_cli-0.1.3.dist-info/RECORD
