Metadata-Version: 2.2
Name: ask-connect-cli
Version: 0.1.3
Summary: A CLI to interact with Google Gemini AI models
Author-email: Jayasurya A <techie4coffee@gmail.com>
License: MIT
Requires-Python: >=3.9
Requires-Dist: build>=1.2.2.post1
Requires-Dist: google-generativeai>=0.8.4
Requires-Dist: grpcio==1.67.1
Requires-Dist: grpcio-status==1.67.1
Requires-Dist: inquirerpy>=0.3.4
Requires-Dist: python-dotenv>=1.0.1
Requires-Dist: requests>=2.32.3
Requires-Dist: rich>=13.9.4
Requires-Dist: tabulate>=0.9.0
Requires-Dist: typer>=0.15.1
